README.rst
setup.py
popget/__about__.py
popget/__init__.py
popget/client.py
popget/endpoint.py
popget/errors.py
popget/extratypes.py
popget/utils.py
popget.egg-info/PKG-INFO
popget.egg-info/SOURCES.txt
popget.egg-info/dependency_links.txt
popget.egg-info/requires.txt
popget.egg-info/top_level.txt
popget/conf/__init__.py
popget/conf/defaults.py
popget/nonblocking/__init__.py
popget/nonblocking/threadpool.py