Metadata-Version: 2.1
Name: popget
Version: 1.8.3
Summary: Simple REST-API client for Python.
Home-page: https://github.com/depop/popget
Author: Depop
Author-email: dev@depop.com
License: Apache 2.0
Platform: UNKNOWN
Classifier: Environment :: Web Environment
Classifier: Intended Audience :: Developers
Classifier: License :: OSI Approved :: Apache Software License
Classifier: Operating System :: OS Independent
Classifier: Programming Language :: Python
Classifier: Programming Language :: Python :: 3.6
Classifier: Programming Language :: Python :: 2.7
Provides-Extra: threadpool
